simple_notify_discord/__init__.py
simple_notify_discord/simple_notify_discord.py
simple_notify_discord-0.1.2.dist-info/licenses/LICENSE
simple_notify_discord-0.1.2.dist-info/METADATA
simple_notify_discord-0.1.2.dist-info/WHEEL
simple_notify_discord-0.1.2.dist-info/top_level.txt
simple_notify_discord-0.1.2.dist-info/RECORD
