Metadata-Version: 2.4
Name: Simple-Notify-discord
Version: 0.1.2
Summary: Simple-Notify-discord allows you to simply send a message on Discord via a webhook, it allows you to alert when a process is finished or other depending on your context.
Author-email: CogalTek <mathieurio.contact@gmail.com>
License: MIT License
Requires-Python: >=3.8
License-File: LICENSE
Dynamic: license-file
